km3io/__init__.py
km3io/acoustics.py
km3io/definitions.py
km3io/offline.py
km3io/rootio.py
km3io/tools.py
km3io/version.py
km3io/_definitions/__init__.py
km3io/_definitions/applications.py
km3io/_definitions/daqdatatypes.py
km3io/_definitions/fitparameters.py
km3io/_definitions/mc_header.py
km3io/_definitions/module_status.py
km3io/_definitions/pmt_status.py
km3io/_definitions/reconstruction.py
km3io/_definitions/root.py
km3io/_definitions/trigger.py
km3io/_definitions/trkmembers.py
km3io/_definitions/w2list_genhen.py
km3io/_definitions/w2list_gseagen.py
km3io/_definitions/w2list_km3buu.py
km3io/_definitions/weightlist.py
km3io-1.2.3.dist-info/LICENSE
km3io-1.2.3.dist-info/METADATA
km3io-1.2.3.dist-info/WHEEL
km3io-1.2.3.dist-info/top_level.txt
km3io-1.2.3.dist-info/RECORD
