Metadata-Version: 2.1
Name: km3io
Version: 1.2.3
Summary: "KM3NeT I/O library without ROOT"
Home-page: https://git.km3net.de/km3py/km3io
Author: "Tamas Gal and Zineb Aly"
Author-email: tgal@km3net.de
Maintainer: Tamas Gal
Maintainer-email: tgal@km3net.de
License: MIT
Keywords: neutrino,astroparticle,physics,HEP,root
Platform: UNKNOWN
Classifier: Development Status :: 5 - Production/Stable
Classifier: Intended Audience :: Developers
Classifier: Intended Audience :: Science/Research
Classifier: License :: OSI Approved :: BSD License
Classifier: Operating System :: OS Independent
Classifier: Programming Language :: Python
Classifier: Programming Language :: Python :: 3
Classifier: Programming Language :: Python :: 3 :: Only
Classifier: Programming Language :: Python :: 3.9
Classifier: Programming Language :: Python :: 3.10
Classifier: Programming Language :: Python :: 3.11
Classifier: Programming Language :: Python :: 3.12
Classifier: Topic :: Scientific/Engineering
Requires-Python: >=3.9
Requires-Dist: docopt
Requires-Dist: numba>=0.50
Requires-Dist: awkward>=2
Requires-Dist: numpy>=2
Requires-Dist: uproot>=5
Requires-Dist: setuptools-scm
Provides-Extra: all
Provides-Extra: dev
Requires-Dist: black>=22.3.0; extra == "dev"
Requires-Dist: km3net-testdata>=0.3.6; extra == "dev"
Requires-Dist: ipykernel; extra == "dev"
Requires-Dist: matplotlib; extra == "dev"
Requires-Dist: memory-profiler; extra == "dev"
Requires-Dist: numpydoc; extra == "dev"
Requires-Dist: pillow; extra == "dev"
Requires-Dist: pytest; extra == "dev"
Requires-Dist: pytest-cov; extra == "dev"
Requires-Dist: pytest-flake8; extra == "dev"
Requires-Dist: pylint; extra == "dev"
Requires-Dist: pytest-watch; extra == "dev"
Requires-Dist: scipy; extra == "dev"
Requires-Dist: sphinx; extra == "dev"
Requires-Dist: sphinx-autoapi; extra == "dev"
Requires-Dist: sphinx-gallery; extra == "dev"
Requires-Dist: sphinx-rtd-theme; extra == "dev"
Requires-Dist: sphinxcontrib-versioning; extra == "dev"
Requires-Dist: wheel; extra == "dev"
